ml_botting_core/__init__.py
ml_botting_core/base.py
ml_botting_core/classification/__init__.py
ml_botting_core/classification/universal_classifier_trainer.py
ml_botting_core/general/__init__.py
ml_botting_core/general/general.py
ml_botting_core/model_management/__init__.py
ml_botting_core/model_management/download_models.py
ml_botting_core/model_management/load_models.py
ml_botting_core/model_management/model_manager.py
ml_botting_core/prediction/__init__.py
ml_botting_core/prediction/prediction.py
ml_botting_core/regression/__init__.py
ml_botting_core/regression/universal_regressor.py
ml_botting_core-1.0.7.dist-info/LICENSE
ml_botting_core-1.0.7.dist-info/METADATA
ml_botting_core-1.0.7.dist-info/WHEEL
ml_botting_core-1.0.7.dist-info/top_level.txt
ml_botting_core-1.0.7.dist-info/RECORD
