Metadata-Version: 2.1
Name: ml-botting-core
Version: 1.0.7
Summary: Making ML more accessible to botting apps. Solving Complex UI Challenges w/ ML.
Home-page: https://github.com/darkmatter2222/ml_botting_core
Author: Ryan Susman
Author-email: ryansusman@gmail.com
Project-URL: Bug Tracker, https://github.com/darkmatter2222/ml_botting_core/issues
Classifier: Programming Language :: Python :: 3
Classifier: License :: OSI Approved :: MIT License
Classifier: Operating System :: OS Independent
Requires-Python: >=3.6
License-File: LICENSE
